darcyforchheimer.py
darcyforchheimer-0.0.2.dist-info/LICENSE.txt
darcyforchheimer-0.0.2.dist-info/METADATA
darcyforchheimer-0.0.2.dist-info/WHEEL
darcyforchheimer-0.0.2.dist-info/top_level.txt
darcyforchheimer-0.0.2.dist-info/RECORD
