Metadata-Version: 2.1
Name: darcyforchheimer
Version: 0.0.2
Summary: darcy-forchheimer parameters calculator helper
Home-page: https://github.com/Hynack/darcyforchheimer
Author: David Hinojosa
Author-email: hynack@gmail.com
License: UNKNOWN
Platform: UNKNOWN
Requires-Dist: scipy (~=1.6)
Provides-Extra: dev
Requires-Dist: pytest (>=6.2.3) ; extra == 'dev'
